{
    "key": "group_67eefcbc548c8",
    "title": "Matchmaking",
    "fields": [
        {
            "key": "field_67eefcbce9b17",
            "label": "Question One",
            "name": "question_one",
            "aria-label": "",
            "type": "radio",
            "instructions": "",
            "required": 1,
            "conditional_logic": 0,
            "wrapper": {
                "width": "",
                "class": "",
                "id": ""
            },
            "choices": {
                "one": "Option One",
                "two": "Option Two"
            },
            "default_value": "",
            "return_format": "value",
            "allow_null": 1,
            "other_choice": 0,
            "allow_in_bindings": 0,
            "layout": "horizontal",
            "save_other_choice": 0
        },
        {
            "key": "field_67eefd5fe9b18",
            "label": "Question Two",
            "name": "question_two",
            "aria-label": "",
            "type": "radio",
            "instructions": "",
            "required": 1,
            "conditional_logic": 0,
            "wrapper": {
                "width": "",
                "class": "",
                "id": ""
            },
            "choices": {
                "one": "Option One",
                "two": "Option Two"
            },
            "default_value": "",
            "return_format": "value",
            "allow_null": 1,
            "other_choice": 0,
            "allow_in_bindings": 0,
            "layout": "horizontal",
            "save_other_choice": 0
        },
        {
            "key": "field_67eefd72e9b1a",
            "label": "Question Three",
            "name": "question_three",
            "aria-label": "",
            "type": "radio",
            "instructions": "",
            "required": 1,
            "conditional_logic": 0,
            "wrapper": {
                "width": "",
                "class": "",
                "id": ""
            },
            "choices": {
                "one": "Option One",
                "two": "Option Two"
            },
            "default_value": "",
            "return_format": "value",
            "allow_null": 1,
            "other_choice": 0,
            "allow_in_bindings": 0,
            "layout": "horizontal",
            "save_other_choice": 0
        },
        {
            "key": "field_67eefd8fe9b1c",
            "label": "Question Four",
            "name": "question_four",
            "aria-label": "",
            "type": "radio",
            "instructions": "",
            "required": 1,
            "conditional_logic": 0,
            "wrapper": {
                "width": "",
                "class": "",
                "id": ""
            },
            "choices": {
                "one": "Option One",
                "two": "Option Two"
            },
            "default_value": "",
            "return_format": "value",
            "allow_null": 1,
            "other_choice": 0,
            "allow_in_bindings": 0,
            "layout": "horizontal",
            "save_other_choice": 0
        }
    ],
    "location": [
        [
            {
                "param": "post_type",
                "operator": "==",
                "value": "post"
            }
        ]
    ],
    "menu_order": 0,
    "position": "normal",
    "style": "default",
    "label_placement": "left",
    "instruction_placement": "label",
    "hide_on_screen": "",
    "active": true,
    "description": "",
    "show_in_rest": 0,
    "acfe_display_title": "",
    "acfe_autosync": [
        "json"
    ],
    "acfe_form": 0,
    "acfe_meta": "",
    "acfe_note": "",
    "modified": 1743717028
}
